fuckyou_sort/__init__.py
fuckyou_sort/__main__.py
fuckyou_sort/fuckyou_sort.py
fuckyou_sort-1.0.1.dist-info/LICENCE
fuckyou_sort-1.0.1.dist-info/METADATA
fuckyou_sort-1.0.1.dist-info/WHEEL
fuckyou_sort-1.0.1.dist-info/entry_points.txt
fuckyou_sort-1.0.1.dist-info/top_level.txt
fuckyou_sort-1.0.1.dist-info/RECORD
